varvar/__init__.py
varvar/htrees.py
varvar/linear.py
varvar/mvt.py
varvar/predict.py
varvar/qtrees.py
varvar-1.0.0.dist-info/LICENSE
varvar-1.0.0.dist-info/METADATA
varvar-1.0.0.dist-info/WHEEL
varvar-1.0.0.dist-info/top_level.txt
varvar-1.0.0.dist-info/RECORD
