Metadata-Version: 2.1
Name: varvar
Version: 1.0.0
Summary: Model variance with multiplicative variance trees
Home-page: https://github.com/drorspei/varvar
Author: Dror Speiser
License: UNKNOWN
Platform: UNKNOWN
Classifier: Programming Language :: Python :: 3
Classifier: License :: OSI Approved :: MIT License
License-File: LICENSE
Requires-Dist: numpy
Requires-Dist: numba
